MANIFEST.in
README.md
setup.cfg
setup.py
iotlab_radio_test/__init__.py
iotlab_radio_test/aggregate_exp_avg.py
iotlab_radio_test/aggregate_stability.py
iotlab_radio_test/clean.py
iotlab_radio_test/cli.py
iotlab_radio_test/config.py
iotlab_radio_test/connectivity_parser.py
iotlab_radio_test/constants.py
iotlab_radio_test/draw_common.py
iotlab_radio_test/drawer_average.py
iotlab_radio_test/drawer_connectivity.py
iotlab_radio_test/image_generator.py
iotlab_radio_test/nodes.py
iotlab_radio_test/nominal_config.yaml
iotlab_radio_test/raw_log_parser.py
iotlab_radio_test/run.py
iotlab_radio_test/start.py
iotlab_radio_test/topology.py
iotlab_radio_test/utils.py
iotlab_radio_test/valid.py
iotlab_radio_test.egg-info/PKG-INFO
iotlab_radio_test.egg-info/SOURCES.txt
iotlab_radio_test.egg-info/dependency_links.txt
iotlab_radio_test.egg-info/entry_points.txt
iotlab_radio_test.egg-info/requires.txt
iotlab_radio_test.egg-info/top_level.txt
iotlab_radio_test/firmwares/radio_test_m3.elf
tests/__init__.py
tests/test_02_rawparser.py
tests/test_03_connectivity_parser.py
tests/test_04_aggregate.py
tests/test_config_entry.py
tests/test_entrypoint.py