Metadata-Version: 1.0
Name: iotlab-radio-test
Version: 0.1.9
Summary: Nodes Radio Test
Home-page: http://www.iot-lab.info
Author: IoT-Lab Team
Author-email: admin@iot-lab.info
License: CeCILL v2.1
Platform: UNKNOWN
